xin2pbn/__init__.py
xin2pbn/demo.pbn
xin2pbn/template.pbn
xin2pbn/xin2pbn.py
xin2pbn-0.1.18.dist-info/METADATA
xin2pbn-0.1.18.dist-info/WHEEL
xin2pbn-0.1.18.dist-info/entry_points.txt
xin2pbn-0.1.18.dist-info/top_level.txt
xin2pbn-0.1.18.dist-info/RECORD
