Metadata-Version: 2.1
Name: xin2pbn
Version: 0.1.18
Summary: converter from xinrui url to pbn files
Home-page: https://github.com/larrycai/xin2pbn
Author: Larry Cai
Author-email: larry.caiyu@gmail.com
License: UNKNOWN
Platform: UNKNOWN
Classifier: Programming Language :: Python :: 3
Classifier: License :: OSI Approved :: MIT License
Classifier: Operating System :: OS Independent
Requires-Python: >=3.6
